usbpdparser/__init__.py
usbpdparser/core.py
usbpdparser/core.pyi
usbpdparser/tools/__init__.py
usbpdparser/tools/render.py
usbpdparser/tools/render.pyi
usbpdparser/tools/vendor_ids_dict.py
usbpdparser-1.1.4.dist-info/licenses/LICENSE
usbpdparser-1.1.4.dist-info/METADATA
usbpdparser-1.1.4.dist-info/WHEEL
usbpdparser-1.1.4.dist-info/top_level.txt
usbpdparser-1.1.4.dist-info/RECORD
