Metadata-Version: 2.4
Name: usbpdparser
Version: 1.1.4
Summary: A Python API for parsing USB Power Delivery messages.
Author-email: JohnScott <ruaorz@gmail.com>
License: LGPL-3.0-or-later
Project-URL: Homepage, https://github.com/JohnScotttt/USB_PD_Parser_API_Py
Requires-Python: >=3.10
License-File: LICENSE
Dynamic: license-file
